http_logging/__init__.py
http_logging/constants.py
http_logging/formatter.py
http_logging/handler.py
http_logging/secondary_classes.py
http_logging/transport.py
http_logging-2.0.0.dist-info/LICENSE
http_logging-2.0.0.dist-info/METADATA
http_logging-2.0.0.dist-info/WHEEL
http_logging-2.0.0.dist-info/top_level.txt
http_logging-2.0.0.dist-info/RECORD
