Metadata-Version: 2.1
Name: http-logging
Version: 2.0.0
Summary: Non-blocking HTTP handler for Python `logging` with local SQLite buffer/cache.
Home-page: https://github.com/hacktlib/py-async-http-logging/wiki
Author: Hackt.app
Author-email: opensource@hackt.app
License: UNKNOWN
Project-URL: Bug Reports, https://github.com/hacktlib/py-async-http-logging/issues
Project-URL: Say Thanks!, http://lib.hackt.app
Project-URL: Source, https://github.com/hacktlib/py-async-http-logging/
Platform: UNKNOWN
Classifier: Development Status :: 4 - Beta
Classifier: Intended Audience :: Developers
Classifier: License :: OSI Approved :: Apache Software License
Classifier: Natural Language :: English
Classifier: Programming Language :: Python :: 3
Classifier: Programming Language :: Python :: 3.6
Classifier: Programming Language :: Python :: 3.7
Classifier: Programming Language :: Python :: 3.8
Classifier: Programming Language :: Python :: 3 :: Only
Classifier: Topic :: Software Development :: Libraries
Classifier: Topic :: Utilities
Requires-Python: >=3.6, <4
Requires-Dist: python-logstash-async (>=2.2.0)
Requires-Dist: requests (>=2.25.1)
Provides-Extra: dev
Requires-Dist: pexpect (>=4.8.0) ; extra == 'dev'
Requires-Dist: autopep8 (>=1.5.4) ; extra == 'dev'
Requires-Dist: flake8 (>=3.8.4) ; extra == 'dev'
Requires-Dist: pytest (>=6.2.1) ; extra == 'dev'
Requires-Dist: coverage (>=5.3) ; extra == 'dev'
Requires-Dist: coverage-badge (>=1.0.1) ; extra == 'dev'
Requires-Dist: wheel (>=0.36.2) ; extra == 'dev'
Provides-Extra: pub
Requires-Dist: pexpect (>=4.8.0) ; extra == 'pub'
Requires-Dist: autopep8 (>=1.5.4) ; extra == 'pub'
Requires-Dist: flake8 (>=3.8.4) ; extra == 'pub'
Requires-Dist: pytest (>=6.2.1) ; extra == 'pub'
Requires-Dist: coverage (>=5.3) ; extra == 'pub'
Requires-Dist: coverage-badge (>=1.0.1) ; extra == 'pub'
Requires-Dist: wheel (>=0.36.2) ; extra == 'pub'
Requires-Dist: twine (>=3.2.0) ; extra == 'pub'
